{"id":"images/gallery/mobile/gallery_left3@2x_mobile.webp","dependencies":[{"name":"C:\\Users\\Legion\\Documents\\GitHub\\ice-team-proj\\package.json","includedInParent":true,"mtime":1639068349343},{"name":"C:\\Users\\Legion\\Documents\\GitHub\\ice-team-proj\\.browserslistrc","includedInParent":true,"mtime":1638460562853}],"generated":{"js":"module.exports = \"/ff9cc20f0c85be73d3746d814d7771d7.webp\";"},"sourceMaps":null,"error":null,"hash":"e36641a5f653f127bec4992924351005","cacheData":{"env":{}}}